[
  {
    "title": "Meccano Meccasaur Programmable Robotic …",
    "price": "$39.98",
    "image": "https://truimg.toysrus.com/product/images/DD6958C6.pt01.zoom.jpg?fit=inside|250:230"
  },
  {
    "title": "Yummy Nummies Candy Shop - Gummies Good…",
    "price": "$1.98",
    "image": "https://truimg.toysrus.com/product/images/5B0153EE.pt01.zoom.jpg?fit=inside|250:230"
  },
  {
    "title": "Hexbug AquaBot Wahoo Fish with Bowl (Co…",
    "price": "$4.98",
    "image": "https://truimg.toysrus.com/product/images/424204E0.pt01.zoom.jpg?fit=inside|250:230"
  },
  {
    "title": "Little Tikes Inflatable Bounce Castle w…",
    "price": "$154.98",
    "image": "https://truimg.toysrus.com/product/images/4F76EBBE.pt01.zoom.jpg?fit=inside|250:230"
  },
  {
    "title": "Minecraft Block 12-inch Mini Backpack -…",
    "image": "https://truimg.toysrus.com/product/images/C5963324.zoom.jpg?fit=inside|250:230"
  },
  {
    "title": "Pie Face Game Despicable Me Minion Made…",
    "price": "$12.48",
    "image": "https://truimg.toysrus.com/product/images/25403035.pt01.zoom.jpg?fit=inside|250:230"
  },
  {
    "title": "FurReal Friends StarLily, My Magical Un…",
    "price": "$79.98",
    "image": "https://truimg.toysrus.com/product/images/2788B8FD.pt01.zoom.jpg?fit=inside|250:230"
  },
  {
    "title": "My Little Pony Explore Equestria Crysta…",
    "price": "$24.98",
    "image": "https://truimg.toysrus.com/product/images/C83ED8CD.pt01.zoom.jpg?fit=inside|250:230"
  },
  {
    "title": "Minions Movie Rock N Roll Stuart",
    "price": "$19.98",
    "image": "https://truimg.toysrus.com/product/images/2A10E126.pt01.zoom.jpg?fit=inside|250:230"
  },
  {
    "title": "Fisher-Price Laugh & Learn Smart Stages…",
    "price": "$24.98",
    "image": "https://truimg.toysrus.com/product/images/A2E54711.pt01.zoom.jpg?fit=inside|250:230"
  },
  {
    "title": "Playskool Heroes Transformers Rescue Bo…",
    "price": "$19.98",
    "image": "https://truimg.toysrus.com/product/images/28270520.pt01.zoom.jpg?fit=inside|250:230"
  },
  {
    "title": "Play-Doh Disney Princess Ariel and Unde…",
    "price": "$5.98",
    "image": "https://truimg.toysrus.com/product/images/0279D033.pt01.zoom.jpg?fit=inside|250:230"
  },
  {
    "title": "Miles From Tomorrowland Stellosphere",
    "price": "$19.98",
    "image": "https://truimg.toysrus.com/product/images/30BC1BEB.pt06.zoom.jpg?fit=inside|250:230"
  },
  {
    "title": "Squinkies Squinkieville Vehicle Set - A…",
    "price": "$4.98",
    "image": "https://truimg.toysrus.com/product/images/782711C1.pt01.zoom.jpg?fit=inside|250:230"
  },
  {
    "title": "My Little Pony 4.5 inch Equestria Girls…",
    "price": "$3.98",
    "image": "https://truimg.toysrus.com/product/images/DDC63582.pt01.zoom.jpg?fit=inside|250:230"
  },
  {
    "title": "Melissa & Doug Magnetic Chalkboard and …",
    "price": "$12.98",
    "image": "https://truimg.toysrus.com/product/images/FDE2C73F.pt01.zoom.jpg?fit=inside|250:230"
  },
  {
    "title": "Barbie Sparkle Style Salon Doll Playset…",
    "price": "$19.98",
    "image": "https://truimg.toysrus.com/product/images/C9B86794.pt01.zoom.jpg?fit=inside|250:230"
  },
  {
    "title": "Fisher-Price Nickelodeon Blaze and the …",
    "price": "$4.98",
    "image": "https://truimg.toysrus.com/product/images/387FFEBC.pt01.zoom.jpg?fit=inside|250:230"
  },
  {
    "title": "Step2 Floor to Door Basketball",
    "price": "$17.99",
    "image": "https://truimg.toysrus.com/product/images/254B54AE.zoom.jpg?fit=inside|250:230"
  },
  {
    "title": "Little Tikes Light 'n Go Activity Garde…",
    "price": "$56.98",
    "image": "https://truimg.toysrus.com/product/images/A5B24BD3.pt01.zoom.jpg?fit=inside|250:230"
  },
  {
    "title": "Disney Pixar Collectible Figure - Mr. I…",
    "price": "$3.98",
    "image": "https://truimg.toysrus.com/product/images/3DD17343.zoom.jpg?fit=inside|250:230"
  },
  {
    "title": "Zoomer Chimp Interactive Chimp - Untame…",
    "price": "$49.98",
    "image": "https://truimg.toysrus.com/product/images/F4F41057.pt01.zoom.jpg?fit=inside|250:230"
  },
  {
    "title": "Dr. Seuss Thing Two and Thing One Whirl…",
    "price": "$7.98",
    "image": "https://truimg.toysrus.com/product/images/0497C66C.pt01.zoom.jpg?fit=inside|250:230"
  }
]